xmrto_wrapper/__init__.py
xmrto_wrapper/_logo.py
xmrto_wrapper/_version.py
xmrto_wrapper/rand_ip.py
xmrto_wrapper/xmrto_wrapper.py
xmrto_wrapper-0.3.0.data/scripts/xmrto_wrapper
xmrto_wrapper-0.3.0.dist-info/LICENSE
xmrto_wrapper-0.3.0.dist-info/METADATA
xmrto_wrapper-0.3.0.dist-info/WHEEL
xmrto_wrapper-0.3.0.dist-info/top_level.txt
xmrto_wrapper-0.3.0.dist-info/RECORD
