Metadata-Version: 2.1
Name: xmrto-wrapper
Version: 0.3.0
Summary: Interact with XMR.to, create and track your orders.
Home-page: https://github.com/monero-ecosystem/xmrto_wrapper
Author: Norman Moeschter-Schenck
Author-email: norman.moeschter@gmail.com
License: UNKNOWN
Download-URL: https://github.com/monero-ecosystem/xmrto_wrapper/archive/v0.3.0.tar.gz
Platform: UNKNOWN
Classifier: Development Status :: 5 - Production/Stable
Classifier: Intended Audience :: Developers
Classifier: License :: OSI Approved :: MIT License
Classifier: Natural Language :: English
Classifier: Programming Language :: Python
Requires-Dist: requests (>=2.23.0)
